jotter/__init__.py
jotter/cli.py
jotter/init.py
jotter/note.py
jotter/project.py
jotter/set_remote.py
jotter/sync.py
jotter/util.py
jotter-0.1.3.dist-info/entry_points.txt
jotter-0.1.3.dist-info/LICENSE
jotter-0.1.3.dist-info/WHEEL
jotter-0.1.3.dist-info/METADATA
jotter-0.1.3.dist-info/RECORD
